syftbox_sdk/__init__.py
syftbox_sdk/syftbox_sdk.abi3.so
syftbox_sdk-0.1.15.dist-info/METADATA
syftbox_sdk-0.1.15.dist-info/WHEEL
syftbox_sdk-0.1.15.dist-info/RECORD
