Metadata-Version: 2.4
Name: syftbox-sdk
Version: 0.1.15
Classifier: Programming Language :: Rust
Classifier: Programming Language :: Python
Classifier: Programming Language :: Python :: 3
Classifier: Programming Language :: Python :: 3 :: Only
Classifier: Programming Language :: Python :: 3.13
Classifier: License :: OSI Approved :: Apache Software License
Classifier: Operating System :: OS Independent
Summary: Python bindings for the syftbox-sdk Rust library
Author: OpenMined
License: Apache-2.0
Requires-Python: >=3.8, <3.14
Project-URL: Homepage, https://github.com/OpenMined/syftbox-sdk
